dibuk/__init__.py
dibuk/error.py
dibuk/resource.py
dibuk/version.py
dibuk-0.5.0.dist-info/LICENSE
dibuk-0.5.0.dist-info/METADATA
dibuk-0.5.0.dist-info/WHEEL
dibuk-0.5.0.dist-info/top_level.txt
dibuk-0.5.0.dist-info/RECORD
