Metadata-Version: 2.1
Name: dibuk
Version: 0.5.0
Summary: Dibuk Python Bindings
Author: Palo Sopko
Author-email: pavol@sopko.sk
License: MIT
Project-URL: Bug Tracker, https://github.com/palosopko/dibuk-python/issues
Project-URL: Source Code, https://github.com/palosopko/dibuk-python
Classifier: Development Status :: 5 - Production/Stable
Classifier: Intended Audience :: Developers
Classifier: Natural Language :: English
Classifier: License :: OSI Approved :: MIT License
Classifier: Operating System :: OS Independent
Classifier: Programming Language :: Python
Classifier: Programming Language :: Python :: 3
Classifier: Programming Language :: Python :: 3.6
Classifier: Programming Language :: Python :: 3.7
Classifier: Programming Language :: Python :: 3.8
Classifier: Programming Language :: Python :: 3.9
Classifier: Programming Language :: Python :: 3.10
Classifier: Programming Language :: Python :: 3.11
Classifier: Programming Language :: Python :: Implementation :: PyPy
Classifier: Topic :: Software Development :: Libraries :: Python Modules
Requires-Python: >=3.6
License-File: LICENSE
Requires-Dist: requests >=2.21.0
